Workbook

Sheet Dashboard

Sheet Forecast 
A1: Month | B1: Actual Sales | E1: 2024-2025 Range | F1: Acutal Sales | G1: ETS Forcast | H1: ETS + | I1: Upper | J1: Lower | K1: Linear | L1: Seasonal Naive
A2: 44197 | B2: =SUMIFS(Monthly_Category[sum_sale_dollars], Monthly_Category[Start of Month], A2) -> 28665660 | E2: =EDATE(A37,1) -> 45292 | F2: =SUMIFS(Monthly_Category[sum_sale_dollars], Monthly_Category[Start of Month], E2) -> 32972813 | G2: =_xlfn.FORECAST.ETS(E2,$B$2:$B$37,$A$2:$A$37,12,1) -> 29640677 | H2: =_xlfn.FORECAST.ETS.CONFINT(E2,$B$2:$B$37,$A$2:$A$37,0.95,12,1) -> 4102515 | I2: =G2+H2 -> 33743192 | J2: =G2-H2 -> 25538162 | K2: =_xlfn.FORECAST.LINEAR(E2,$B$2:$B$37,$A$2:$A$37) -> 39043295 | L2: =B26 -> 32547785 | N2: 2024
A3: =EDATE(A2,1) -> 44228 | B3: =SUMIFS(Monthly_Category[sum_sale_dollars], Monthly_Category[Start of Month], A3) -> 29617806 | E3: =EDATE(A38,1) -> 45323 | F3: =SUMIFS(Monthly_Category[sum_sale_dollars], Monthly_Category[Start of Month], E3) -> 35101475 | G3: =_xlfn.FORECAST.ETS(E3,$B$2:$B$37,$A$2:$A$37,12,1) -> 30526623 | H3: =_xlfn.FORECAST.ETS.CONFINT(E3,$B$2:$B$37,$A$2:$A$37,0.95,12,1) -> 4230773.2 | I3: =G3+H3 -> 34757396 | J3: =G3-H3 -> 26295850 | K3: =_xlfn.FORECAST.LINEAR(E3,$B$2:$B$37,$A$2:$A$37) -> 39200059 | L3: =B27 -> 32114831 | N3: ETS Average | O3: Linear Avergae | P3: Navie Average
A4: =EDATE(A3,1) -> 44256 | B4: =SUMIFS(Monthly_Category[sum_sale_dollars], Monthly_Category[Start of Month], A4) -> 36654829 | E4: =EDATE(A39,1) -> 45352 | F4: =SUMIFS(Monthly_Category[sum_sale_dollars], Monthly_Category[Start of Month], E4) -> 34164169 | G4: =_xlfn.FORECAST.ETS(E4,$B$2:$B$37,$A$2:$A$37,12,1) -> 33043871 | H4: =_xlfn.FORECAST.ETS.CONFINT(E4,$B$2:$B$37,$A$2:$A$37,0.95,12,1) -> 4356231.6 | I4: =G4+H4 -> 37400102 | J4: =G4-H4 -> 28687639 | K4: =_xlfn.FORECAST.LINEAR(E4,$B$2:$B$37,$A$2:$A$37) -> 39346709 | L4: =B28 -> 36403506 | N4: {=AVERAGE(ABS((F2:F13-G2:G13)/F2:F13))} -> 0.068073699 | O4: {=AVERAGE(ABS((F2:F13-K2:K13)/F2:F13))} -> 0.086477218 | P4: {=AVERAGE((ABS(F2:F13-L2:L13)/F2:F13))} -> 0.052163643
A5: =EDATE(A4,1) -> 44287 | B5: =SUMIFS(Monthly_Category[sum_sale_dollars], Monthly_Category[Start of Month], A5) -> 34734922 | E5: =EDATE(A40,1) -> 45383 | F5: =SUMIFS(Monthly_Category[sum_sale_dollars], Monthly_Category[Start of Month], E5) -> 36385548 | G5: =_xlfn.FORECAST.ETS(E5,$B$2:$B$37,$A$2:$A$37,12,1) -> 34341901 | H5: =_xlfn.FORECAST.ETS.CONFINT(E5,$B$2:$B$37,$A$2:$A$37,0.95,12,1) -> 4479129.2 | I5: =G5+H5 -> 38821030 | J5: =G5-H5 -> 29862772 | K5: =_xlfn.FORECAST.LINEAR(E5,$B$2:$B$37,$A$2:$A$37) -> 39503474 | L5: =B29 -> 32884344
A6: =EDATE(A5,1) -> 44317 | B6: =SUMIFS(Monthly_Category[sum_sale_dollars], Monthly_Category[Start of Month], A6) -> 33659555 | E6: =EDATE(A41,1) -> 45413 | F6: =SUMIFS(Monthly_Category[sum_sale_dollars], Monthly_Category[Start of Month], E6) -> 39359096 | G6: =_xlfn.FORECAST.ETS(E6,$B$2:$B$37,$A$2:$A$37,12,1) -> 36921055 | H6: =_xlfn.FORECAST.ETS.CONFINT(E6,$B$2:$B$37,$A$2:$A$37,0.95,12,1) -> 4599675 | I6: =G6+H6 -> 41520730 | J6: =G6-H6 -> 32321380 | K6: =_xlfn.FORECAST.LINEAR(E6,$B$2:$B$37,$A$2:$A$37) -> 39655181 | L6: =B30 -> 39684934
A7: =EDATE(A6,1) -> 44348 | B7: =SUMIFS(Monthly_Category[sum_sale_dollars], Monthly_Category[Start of Month], A7) -> 38890929 | E7: =EDATE(A42,1) -> 45444 | F7: =SUMIFS(Monthly_Category[sum_sale_dollars], Monthly_Category[Start of Month], E7) -> 36769358 | G7: =_xlfn.FORECAST.ETS(E7,$B$2:$B$37,$A$2:$A$37,12,1) -> 39843077 | H7: =_xlfn.FORECAST.ETS.CONFINT(E7,$B$2:$B$37,$A$2:$A$37,0.95,12,1) -> 4718052.8 | I7: =G7+H7 -> 44561130 | J7: =G7-H7 -> 35125024 | K7: =_xlfn.FORECAST.LINEAR(E7,$B$2:$B$37,$A$2:$A$37) -> 39811945 | L7: =B31 -> 41194749 | N7: 2025
A8: =EDATE(A7,1) -> 44378 | B8: =SUMIFS(Monthly_Category[sum_sale_dollars], Monthly_Category[Start of Month], A8) -> 35176468 | E8: =EDATE(A43,1) -> 45474 | F8: =SUMIFS(Monthly_Category[sum_sale_dollars], Monthly_Category[Start of Month], E8) -> 37563558 | G8: =_xlfn.FORECAST.ETS(E8,$B$2:$B$37,$A$2:$A$37,12,1) -> 35306060 | H8: =_xlfn.FORECAST.ETS.CONFINT(E8,$B$2:$B$37,$A$2:$A$37,0.95,12,1) -> 4834425.4 | I8: =G8+H8 -> 40140486 | J8: =G8-H8 -> 30471635 | K8: =_xlfn.FORECAST.LINEAR(E8,$B$2:$B$37,$A$2:$A$37) -> 39963652 | L8: =B32 -> 35839000 | N8: ETS Average | O8: Linear Avergae | P8: Navie Average
A9: =EDATE(A8,1) -> 44409 | B9: =SUMIFS(Monthly_Category[sum_sale_dollars], Monthly_Category[Start of Month], A9) -> 36501799 | E9: =EDATE(A44,1) -> 45505 | F9: =SUMIFS(Monthly_Category[sum_sale_dollars], Monthly_Category[Start of Month], E9) -> 36529981 | G9: =_xlfn.FORECAST.ETS(E9,$B$2:$B$37,$A$2:$A$37,12,1) -> 39889380 | H9: =_xlfn.FORECAST.ETS.CONFINT(E9,$B$2:$B$37,$A$2:$A$37,0.95,12,1) -> 4948937.5 | I9: =G9+H9 -> 44838317 | J9: =G9-H9 -> 34940442 | K9: =_xlfn.FORECAST.LINEAR(E9,$B$2:$B$37,$A$2:$A$37) -> 40120416 | L9: =B33 -> 39788044 | N9: {=AVERAGE(ABS((F14:F25-G14:G25)/F14:F25))} -> 0.072524333 | O9: {=AVERAGE(ABS((F14:F25-K14:K25)/F14:F25))} -> 0.12880061 | P9: {=AVERAGE(ABS((F14:F25-L14:L25)/F14:F25))} -> 0.059718261
A10: =EDATE(A9,1) -> 44440 | B10: =SUMIFS(Monthly_Category[sum_sale_dollars], Monthly_Category[Start of Month], A10) -> 35837061 | E10: =EDATE(A45,1) -> 45536 | F10: =SUMIFS(Monthly_Category[sum_sale_dollars], Monthly_Category[Start of Month], E10) -> 34410490 | G10: =_xlfn.FORECAST.ETS(E10,$B$2:$B$37,$A$2:$A$37,12,1) -> 36606305 | H10: =_xlfn.FORECAST.ETS.CONFINT(E10,$B$2:$B$37,$A$2:$A$37,0.95,12,1) -> 5061718.9 | I10: =G10+H10 -> 41668023 | J10: =G10-H10 -> 31544586 | K10: =_xlfn.FORECAST.LINEAR(E10,$B$2:$B$37,$A$2:$A$37) -> 40277180 | L10: =B34 -> 35096964
A11: =EDATE(A10,1) -> 44470 | B11: =SUMIFS(Monthly_Category[sum_sale_dollars], Monthly_Category[Start of Month], A11) -> 38085762 | E11: =EDATE(A46,1) -> 45566 | F11: =SUMIFS(Monthly_Category[sum_sale_dollars], Monthly_Category[Start of Month], E11) -> 42691915 | G11: =_xlfn.FORECAST.ETS(E11,$B$2:$B$37,$A$2:$A$37,12,1) -> 40144177 | H11: =_xlfn.FORECAST.ETS.CONFINT(E11,$B$2:$B$37,$A$2:$A$37,0.95,12,1) -> 5172885.9 | I11: =G11+H11 -> 45317063 | J11: =G11-H11 -> 34971291 | K11: =_xlfn.FORECAST.LINEAR(E11,$B$2:$B$37,$A$2:$A$37) -> 40428888 | L11: =B35 -> 40281759 | N11: 2025 Forecast accuracy
A12: =EDATE(A11,1) -> 44501 | B12: =SUMIFS(Monthly_Category[sum_sale_dollars], Monthly_Category[Start of Month], A12) -> 38007978 | E12: =EDATE(A47,1) -> 45597 | F12: =SUMIFS(Monthly_Category[sum_sale_dollars], Monthly_Category[Start of Month], E12) -> 40090042 | G12: =_xlfn.FORECAST.ETS(E12,$B$2:$B$37,$A$2:$A$37,12,1) -> 38970460 | H12: =_xlfn.FORECAST.ETS.CONFINT(E12,$B$2:$B$37,$A$2:$A$37,0.95,12,1) -> 5282543.7 | I12: =G12+H12 -> 44253004 | J12: =G12-H12 -> 33687917 | K12: =_xlfn.FORECAST.LINEAR(E12,$B$2:$B$37,$A$2:$A$37) -> 40585652 | L12: =B36 -> 39289673 | N12: {=AVERAGE(ABS((F14:F25-L14:L25)/F14:F25))} -> 0.059718261
A13: =EDATE(A12,1) -> 44531 | B13: =SUMIFS(Monthly_Category[sum_sale_dollars], Monthly_Category[Start of Month], A13) -> 42290767 | E13: =EDATE(A48,1) -> 45627 | F13: =SUMIFS(Monthly_Category[sum_sale_dollars], Monthly_Category[Start of Month], E13) -> 41196968 | G13: =_xlfn.FORECAST.ETS(E13,$B$2:$B$37,$A$2:$A$37,12,1) -> 43154721 | H13: =_xlfn.FORECAST.ETS.CONFINT(E13,$B$2:$B$37,$A$2:$A$37,0.95,12,1) -> 5390787.5 | I13: =G13+H13 -> 48545509 | J13: =G13-H13 -> 37763934 | K13: =_xlfn.FORECAST.LINEAR(E13,$B$2:$B$37,$A$2:$A$37) -> 40737359 | L13: =B37 -> 40945073
A14: =EDATE(A13,1) -> 44562 | B14: =SUMIFS(Monthly_Category[sum_sale_dollars], Monthly_Category[Start of Month], A14) -> 27597708 | E14: =EDATE(A49,1) -> 45658 | F14: =SUMIFS(Monthly_Category[sum_sale_dollars], Monthly_Category[Start of Month], E14) -> 31111678 | G14: =_xlfn.FORECAST.ETS(E14,$B$2:$B$49,$A$2:$A$49,12,1) -> 31691741 | H14: =_xlfn.FORECAST.ETS.CONFINT(E14,$B$2:$B$49,$A$2:$A$49,0.95,12,1) -> 3804596 | I14: =G14+H14 -> 35496337 | J14: =G14-H14 -> 27887145 | K14: =_xlfn.FORECAST.LINEAR(E14,$B$2:$B$49,$A$2:$A$49) -> 38908950 | L14: =F2 -> 32972813
A15: =EDATE(A14,1) -> 44593 | B15: =SUMIFS(Monthly_Category[sum_sale_dollars], Monthly_Category[Start of Month], A15) -> 29474101 | E15: =EDATE(A50,1) -> 45689 | F15: =SUMIFS(Monthly_Category[sum_sale_dollars], Monthly_Category[Start of Month], E15) -> 31308696 | G15: =_xlfn.FORECAST.ETS(E15,$B$2:$B$49,$A$2:$A$49,12,1) -> 32646957 | H15: =_xlfn.FORECAST.ETS.CONFINT(E15,$B$2:$B$49,$A$2:$A$49,0.95,12,1) -> 3804613.1 | I15: =G15+H15 -> 36451571 | J15: =G15-H15 -> 28842344 | K15: =_xlfn.FORECAST.LINEAR(E15,$B$2:$B$49,$A$2:$A$49) -> 39010496 | L15: =F3 -> 35101475
A16: =EDATE(A15,1) -> 44621 | B16: =SUMIFS(Monthly_Category[sum_sale_dollars], Monthly_Category[Start of Month], A16) -> 30225875 | E16: =EDATE(A51,1) -> 45717 | F16: =SUMIFS(Monthly_Category[sum_sale_dollars], Monthly_Category[Start of Month], E16) -> 33518799 | G16: =_xlfn.FORECAST.ETS(E16,$B$2:$B$49,$A$2:$A$49,12,1) -> 35207718 | H16: =_xlfn.FORECAST.ETS.CONFINT(E16,$B$2:$B$49,$A$2:$A$49,0.95,12,1) -> 3804643.6 | I16: =G16+H16 -> 39012362 | J16: =G16-H16 -> 31403075 | K16: =_xlfn.FORECAST.LINEAR(E16,$B$2:$B$49,$A$2:$A$49) -> 39102215 | L16: =F4 -> 34164169
A17: =EDATE(A16,1) -> 44652 | B17: =SUMIFS(Monthly_Category[sum_sale_dollars], Monthly_Category[Start of Month], A17) -> 34781762 | E17: =EDATE(A52,1) -> 45748 | F17: =SUMIFS(Monthly_Category[sum_sale_dollars], Monthly_Category[Start of Month], E17) -> 35499986 | G17: =_xlfn.FORECAST.ETS(E17,$B$2:$B$49,$A$2:$A$49,12,1) -> 35650394 | H17: =_xlfn.FORECAST.ETS.CONFINT(E17,$B$2:$B$49,$A$2:$A$49,0.95,12,1) -> 3804691.1 | I17: =G17+H17 -> 39455085 | J17: =G17-H17 -> 31845703 | K17: =_xlfn.FORECAST.LINEAR(E17,$B$2:$B$49,$A$2:$A$49) -> 39203761 | L17: =F5 -> 36385548
A18: =EDATE(A17,1) -> 44682 | B18: =SUMIFS(Monthly_Category[sum_sale_dollars], Monthly_Category[Start of Month], A18) -> 35948167 | E18: =EDATE(A53,1) -> 45778 | F18: =SUMIFS(Monthly_Category[sum_sale_dollars], Monthly_Category[Start of Month], E18) -> 35589683 | G18: =_xlfn.FORECAST.ETS(E18,$B$2:$B$49,$A$2:$A$49,12,1) -> 39109325 | H18: =_xlfn.FORECAST.ETS.CONFINT(E18,$B$2:$B$49,$A$2:$A$49,0.95,12,1) -> 3804759.6 | I18: =G18+H18 -> 42914085 | J18: =G18-H18 -> 35304566 | K18: =_xlfn.FORECAST.LINEAR(E18,$B$2:$B$49,$A$2:$A$49) -> 39302031 | L18: =F6 -> 39359096
A19: =EDATE(A18,1) -> 44713 | B19: =SUMIFS(Monthly_Category[sum_sale_dollars], Monthly_Category[Start of Month], A19) -> 38614152 | E19: =EDATE(A54,1) -> 45809 | F19: =SUMIFS(Monthly_Category[sum_sale_dollars], Monthly_Category[Start of Month], E19) -> 35946281 | G19: =_xlfn.FORECAST.ETS(E19,$B$2:$B$49,$A$2:$A$49,12,1) -> 40711816 | H19: =_xlfn.FORECAST.ETS.CONFINT(E19,$B$2:$B$49,$A$2:$A$49,0.95,12,1) -> 3804852.8 | I19: =G19+H19 -> 44516669 | J19: =G19-H19 -> 36906963 | K19: =_xlfn.FORECAST.LINEAR(E19,$B$2:$B$49,$A$2:$A$49) -> 39403577 | L19: =F7 -> 36769358
A20: =EDATE(A19,1) -> 44743 | B20: =SUMIFS(Monthly_Category[sum_sale_dollars], Monthly_Category[Start of Month], A20) -> 33792893 | E20: =EDATE(A55,1) -> 45839 | F20: =SUMIFS(Monthly_Category[sum_sale_dollars], Monthly_Category[Start of Month], E20) -> 36094242 | G20: =_xlfn.FORECAST.ETS(E20,$B$2:$B$49,$A$2:$A$49,12,1) -> 36873441 | H20: =_xlfn.FORECAST.ETS.CONFINT(E20,$B$2:$B$49,$A$2:$A$49,0.95,12,1) -> 3804974.5 | I20: =G20+H20 -> 40678415 | J20: =G20-H20 -> 33068466 | K20: =_xlfn.FORECAST.LINEAR(E20,$B$2:$B$49,$A$2:$A$49) -> 39501848 | L20: =F8 -> 37563558
A21: =EDATE(A20,1) -> 44774 | B21: =SUMIFS(Monthly_Category[sum_sale_dollars], Monthly_Category[Start of Month], A21) -> 41374068 | E21: =EDATE(A56,1) -> 45870 | F21: =SUMIFS(Monthly_Category[sum_sale_dollars], Monthly_Category[Start of Month], E21) -> 34213226 | G21: =_xlfn.FORECAST.ETS(E21,$B$2:$B$49,$A$2:$A$49,12,1) -> 40557852 | H21: =_xlfn.FORECAST.ETS.CONFINT(E21,$B$2:$B$49,$A$2:$A$49,0.95,12,1) -> 3805128.6 | I21: =G21+H21 -> 44362981 | J21: =G21-H21 -> 36752724 | K21: =_xlfn.FORECAST.LINEAR(E21,$B$2:$B$49,$A$2:$A$49) -> 39603394 | L21: =F9 -> 36529981
A22: =EDATE(A21,1) -> 44805 | B22: =SUMIFS(Monthly_Category[sum_sale_dollars], Monthly_Category[Start of Month], A22) -> 36622694 | E22: =EDATE(A57,1) -> 45901 | F22: =SUMIFS(Monthly_Category[sum_sale_dollars], Monthly_Category[Start of Month], E22) -> 35151176 | G22: =_xlfn.FORECAST.ETS(E22,$B$2:$B$49,$A$2:$A$49,12,1) -> 37672559 | H22: =_xlfn.FORECAST.ETS.CONFINT(E22,$B$2:$B$49,$A$2:$A$49,0.95,12,1) -> 3805318.8 | I22: =G22+H22 -> 41477878 | J22: =G22-H22 -> 33867240 | K22: =_xlfn.FORECAST.LINEAR(E22,$B$2:$B$49,$A$2:$A$49) -> 39704940 | L22: =F10 -> 34410490
A23: =EDATE(A22,1) -> 44835 | B23: =SUMIFS(Monthly_Category[sum_sale_dollars], Monthly_Category[Start of Month], A23) -> 39688633 | E23: =EDATE(A58,1) -> 45931 | F23: =SUMIFS(Monthly_Category[sum_sale_dollars], Monthly_Category[Start of Month], E23) -> 40038768 | G23: =_xlfn.FORECAST.ETS(E23,$B$2:$B$49,$A$2:$A$49,12,1) -> 41353565 | H23: =_xlfn.FORECAST.ETS.CONFINT(E23,$B$2:$B$49,$A$2:$A$49,0.95,12,1) -> 3805548.9 | I23: =G23+H23 -> 45159114 | J23: =G23-H23 -> 37548016 | K23: =_xlfn.FORECAST.LINEAR(E23,$B$2:$B$49,$A$2:$A$49) -> 39803210 | L23: =F11 -> 42691915
A24: =EDATE(A23,1) -> 44866 | B24: =SUMIFS(Monthly_Category[sum_sale_dollars], Monthly_Category[Start of Month], A24) -> 37513439 | E24: =EDATE(A59,1) -> 45962 | F24: =SUMIFS(Monthly_Category[sum_sale_dollars], Monthly_Category[Start of Month], E24) -> 34684681 | G24: =_xlfn.FORECAST.ETS(E24,$B$2:$B$49,$A$2:$A$49,12,1) -> 39963592 | H24: =_xlfn.FORECAST.ETS.CONFINT(E24,$B$2:$B$49,$A$2:$A$49,0.95,12,1) -> 3805822.8 | I24: =G24+H24 -> 43769415 | J24: =G24-H24 -> 36157769 | K24: =_xlfn.FORECAST.LINEAR(E24,$B$2:$B$49,$A$2:$A$49) -> 39904756 | L24: =F12 -> 40090042
A25: =EDATE(A24,1) -> 44896 | B25: =SUMIFS(Monthly_Category[sum_sale_dollars], Monthly_Category[Start of Month], A25) -> 43146512 | E25: =EDATE(A60,1) -> 45992 | F25: =SUMIFS(Monthly_Category[sum_sale_dollars], Monthly_Category[Start of Month], E25) -> 41657070 | G25: =_xlfn.FORECAST.ETS(E25,$B$2:$B$49,$A$2:$A$49,12,1) -> 44115417 | H25: =_xlfn.FORECAST.ETS.CONFINT(E25,$B$2:$B$49,$A$2:$A$49,0.95,12,1) -> 3806144.2 | I25: =G25+H25 -> 47921561 | J25: =G25-H25 -> 40309272 | K25: =_xlfn.FORECAST.LINEAR(E25,$B$2:$B$49,$A$2:$A$49) -> 40003026 | L25: =F13 -> 41196968
A26: =EDATE(A25,1) -> 44927 | B26: =SUMIFS(Monthly_Category[sum_sale_dollars], Monthly_Category[Start of Month], A26) -> 32547785
A27: =EDATE(A26,1) -> 44958 | B27: =SUMIFS(Monthly_Category[sum_sale_dollars], Monthly_Category[Start of Month], A27) -> 32114831
A28: =EDATE(A27,1) -> 44986 | B28: =SUMIFS(Monthly_Category[sum_sale_dollars], Monthly_Category[Start of Month], A28) -> 36403506
A29: =EDATE(A28,1) -> 45017 | B29: =SUMIFS(Monthly_Category[sum_sale_dollars], Monthly_Category[Start of Month], A29) -> 32884344
A30: =EDATE(A29,1) -> 45047 | B30: =SUMIFS(Monthly_Category[sum_sale_dollars], Monthly_Category[Start of Month], A30) -> 39684934
A31: =EDATE(A30,1) -> 45078 | B31: =SUMIFS(Monthly_Category[sum_sale_dollars], Monthly_Category[Start of Month], A31) -> 41194749
A32: =EDATE(A31,1) -> 45108 | B32: =SUMIFS(Monthly_Category[sum_sale_dollars], Monthly_Category[Start of Month], A32) -> 35839000
A33: =EDATE(A32,1) -> 45139 | B33: =SUMIFS(Monthly_Category[sum_sale_dollars], Monthly_Category[Start of Month], A33) -> 39788044
A34: =EDATE(A33,1) -> 45170 | B34: =SUMIFS(Monthly_Category[sum_sale_dollars], Monthly_Category[Start of Month], A34) -> 35096964
A35: =EDATE(A34,1) -> 45200 | B35: =SUMIFS(Monthly_Category[sum_sale_dollars], Monthly_Category[Start of Month], A35) -> 40281759
A36: =EDATE(A35,1) -> 45231 | B36: =SUMIFS(Monthly_Category[sum_sale_dollars], Monthly_Category[Start of Month], A36) -> 39289673
A37: =EDATE(A36,1) -> 45261 | B37: =SUMIFS(Monthly_Category[sum_sale_dollars], Monthly_Category[Start of Month], A37) -> 40945073
... A61: =EDATE(A60,1) -> 45992 | B61: =SUMIFS(Monthly_Category[sum_sale_dollars], Monthly_Category[Start of Month], A61) -> 41657070

Sheet Scenario Summary
B2: Scenario Summary
D3: Current Values: | E3: Best | F3: Base | G3: Worst
E4: Created by Andres Martinez on 10/17/2026 | F4: Created by Andres Martinez on 10/17/2026 | G4: Created by Andres Martinez on 10/17/2026
B5: Changing Cells:
C6: $B$4 | D6: -0.030249137 | E6: 0.01 | F6: -0.03 | G6: -0.05
C7: $B$5 | D7: -0.020503805 | E7: 0.02 | F7: -0.02 | G7: -0.03
B8: Result Cells:
C9: $B$9 | D9: 4.0351719e+08 | E9: 4.3764368e+08 | F9: 4.0382846e+08 | G9: 3.9146636e+08
C10: $B$10 | D10: -21297096 | E10: 12829391 | F10: -20985826 | G10: -33347921
B11: Notes: Current Values column represents values of changing cells at
B12: time Scenario Summary Report was created. Changing cells for each
B13: scenario are highlighted in gray.

Sheet Model
A2: 2025 Bottles | B2: =PVM!E10 -> 30440723
A3: 2025 Avg Price | B3: =PVM!G10 -> 13.95546 | D3: =B9 -> 4.0382846e+08 | E3: -0.05 | F3: -0.04 | G3: -0.03 | H3: -0.02 | I3: -0.01 | J3: 0 | K3: 0.01 | L3: 0.02 | M3: 0.03 | N3: 0.04 | O3: 0.05
A4: Volume Growth % | B4: -0.03 | D4: -0.05 | E4: 3.8339489e+08 | F4: 3.8743063e+08 | G4: 3.9146636e+08 | H4: 3.955021e+08 | I4: 3.9953784e+08 | J4: 4.0357357e+08 | K4: 4.0760931e+08 | L4: 4.1164504e+08 | M4: 4.1568078e+08 | N4: 4.1971651e+08 | O4: 4.2375225e+08
A5: Price Change % | B5: -0.02 | D5: -0.04 | E5: 3.8743063e+08 | F5: 3.9150885e+08 | G5: 3.9558706e+08 | H5: 3.9966528e+08 | I5: 4.037435e+08 | J5: 4.0782171e+08 | K5: 4.1189993e+08 | L5: 4.1597815e+08 | M5: 4.2005637e+08 | N5: 4.2413458e+08 | O5: 4.282128e+08
D6: -0.03 | E6: 3.9146636e+08 | F6: 3.9558706e+08 | G6: 3.9970776e+08 | H6: 4.0382846e+08 | I6: 4.0794916e+08 | J6: 4.1206986e+08 | K6: 4.1619056e+08 | L6: 4.2031125e+08 | M6: 4.2443195e+08 | N6: 4.2855265e+08 | O6: 4.3267335e+08
A7: 2026 Bottles | B7: =B2*(1+B4) -> 29527501 | D7: -0.02 | E7: 3.955021e+08 | F7: 3.9966528e+08 | G7: 4.0382846e+08 | H7: 4.0799164e+08 | I7: 4.1215482e+08 | J7: 4.16318e+08 | K7: 4.2048118e+08 | L7: 4.2464436e+08 | M7: 4.2880754e+08 | N7: 4.3297072e+08 | O7: 4.371339e+08
A8: 2026 Avg Price | B8: =B3*(1+B5) -> 13.676351 | D8: -0.01 | E8: 3.9953784e+08 | F8: 4.037435e+08 | G8: 4.0794916e+08 | H8: 4.1215482e+08 | I8: 4.1636048e+08 | J8: 4.2056614e+08 | K8: 4.247718e+08 | L8: 4.2897747e+08 | M8: 4.3318313e+08 | N8: 4.3738879e+08 | O8: 4.4159445e+08
A9: 2026 Revenue | B9: =B7*B8 -> 4.0382846e+08 | D9: 0 | E9: 4.0357357e+08 | F9: 4.0782171e+08 | G9: 4.1206986e+08 | H9: 4.16318e+08 | I9: 4.2056614e+08 | J9: 4.2481429e+08 | K9: 4.2906243e+08 | L9: 4.3331057e+08 | M9: 4.3755871e+08 | N9: 4.4180686e+08 | O9: 4.46055e+08
A10: Change Vs 2025 | B10: =B9-PVM!C10 -> -20985826 | D10: 0.01 | E10: 4.0760931e+08 | F10: 4.1189993e+08 | G10: 4.1619056e+08 | H10: 4.2048118e+08 | I10: 4.247718e+08 | J10: 4.2906243e+08 | K10: 4.3335305e+08 | L10: 4.3764368e+08 | M10: 4.419343e+08 | N10: 4.4622493e+08 | O10: 4.5051555e+08
A11: % Change | B11: =B10/PVM!C10 -> -0.0494 | D11: 0.02 | E11: 4.1164504e+08 | F11: 4.1597815e+08 | G11: 4.2031125e+08 | H11: 4.2464436e+08 | I11: 4.2897747e+08 | J11: 4.3331057e+08 | K11: 4.3764368e+08 | L11: 4.4197678e+08 | M11: 4.4630989e+08 | N11: 4.5064299e+08 | O11: 4.549761e+08
D12: 0.03 | E12: 4.1568078e+08 | F12: 4.2005637e+08 | G12: 4.2443195e+08 | H12: 4.2880754e+08 | I12: 4.3318313e+08 | J12: 4.3755871e+08 | K12: 4.419343e+08 | L12: 4.4630989e+08 | M12: 4.5068548e+08 | N12: 4.5506106e+08 | O12: 4.5943665e+08
D13: 0.04 | E13: 4.1971651e+08 | F13: 4.2413458e+08 | G13: 4.2855265e+08 | H13: 4.3297072e+08 | I13: 4.3738879e+08 | J13: 4.4180686e+08 | K13: 4.4622493e+08 | L13: 4.5064299e+08 | M13: 4.5506106e+08 | N13: 4.5947913e+08 | O13: 4.638972e+08
D14: 0.05 | E14: 4.2375225e+08 | F14: 4.282128e+08 | G14: 4.3267335e+08 | H14: 4.371339e+08 | I14: 4.4159445e+08 | J14: 4.46055e+08 | K14: 4.5051555e+08 | L14: 4.549761e+08 | M14: 4.5943665e+08 | N14: 4.638972e+08 | O14: 4.6835775e+08

Sheet Stacked Bar
A1: Category Names | B1: Low (-5%) | C1: High (+5%)
A2: Whiskey | B2: -8141592.1 | C2: 8141592.1
A3: Vodka | B3: -4559262.7 | C3: 4559262.7
A4: Tequila/Mezcal | B4: -2213465.1 | C4: 2213465.1
A5: Liqueurs | B5: -1984981.1 | C5: 1984981.1
A6: Rum | B6: -1692588.8 | C6: 1692588.8
A7: Other | B7: -1586409.1 | C7: 1586409.1
A8: Brandy | B8: -607572.89 | C8: 607572.89
A9: Gin | B9: -454842.57 | C9: 454842.57

Sheet Variance
A1: Month | B1: Plan | C1: Actual | D1: $ Variance | E1: % Variance | F1: Flag
A2: ='Forecast '!E14 -> 45658 | B2: ='Forecast '!L14 -> 32972813 | C2: ='Forecast '!F14 -> 31111678 | D2: =C2-B2 -> -1861135.2 | E2: =IFERROR(D2/B2,0) -> -0.056444538 | F2: =IF(ABS(E2)>0.05,"REVIEW","") -> REVIEW
A3: ='Forecast '!E15 -> 45689 | B3: ='Forecast '!L15 -> 35101475 | C3: ='Forecast '!F15 -> 31308696 | D3: =C3-B3 -> -3792779.7 | E3: =IFERROR(D3/B3,0) -> -0.10805186 | F3: =IF(ABS(E3)>0.05,"REVIEW","") -> REVIEW
A4: ='Forecast '!E16 -> 45717 | B4: ='Forecast '!L16 -> 34164169 | C4: ='Forecast '!F16 -> 33518799 | D4: =C4-B4 -> -645370.68 | E4: =IFERROR(D4/B4,0) -> -0.018890279 | F4: =IF(ABS(E4)>0.05,"REVIEW","")
A5: ='Forecast '!E17 -> 45748 | B5: ='Forecast '!L17 -> 36385548 | C5: ='Forecast '!F17 -> 35499986 | D5: =C5-B5 -> -885561.52 | E5: =IFERROR(D5/B5,0) -> -0.024338276 | F5: =IF(ABS(E5)>0.05,"REVIEW","")
A6: ='Forecast '!E18 -> 45778 | B6: ='Forecast '!L18 -> 39359096 | C6: ='Forecast '!F18 -> 35589683 | D6: =C6-B6 -> -3769412.2 | E6: =IFERROR(D6/B6,0) -> -0.095769786 | F6: =IF(ABS(E6)>0.05,"REVIEW","") -> REVIEW
A7: ='Forecast '!E19 -> 45809 | B7: ='Forecast '!L19 -> 36769358 | C7: ='Forecast '!F19 -> 35946281 | D7: =C7-B7 -> -823077.27 | E7: =IFERROR(D7/B7,0) -> -0.022384869 | F7: =IF(ABS(E7)>0.05,"REVIEW","")
A8: ='Forecast '!E20 -> 45839 | B8: ='Forecast '!L20 -> 37563558 | C8: ='Forecast '!F20 -> 36094242 | D8: =C8-B8 -> -1469315.3 | E8: =IFERROR(D8/B8,0) -> -0.039115447 | F8: =IF(ABS(E8)>0.05,"REVIEW","")
A9: ='Forecast '!E21 -> 45870 | B9: ='Forecast '!L21 -> 36529981 | C9: ='Forecast '!F21 -> 34213226 | D9: =C9-B9 -> -2316754.7 | E9: =IFERROR(D9/B9,0) -> -0.063420638 | F9: =IF(ABS(E9)>0.05,"REVIEW","") -> REVIEW
A10: ='Forecast '!E22 -> 45901 | B10: ='Forecast '!L22 -> 34410490 | C10: ='Forecast '!F22 -> 35151176 | D10: =C10-B10 -> 740685.51 | E10: =IFERROR(D10/B10,0) -> 0.021524992 | F10: =IF(ABS(E10)>0.05,"REVIEW","")
A11: ='Forecast '!E23 -> 45931 | B11: ='Forecast '!L23 -> 42691915 | C11: ='Forecast '!F23 -> 40038768 | D11: =C11-B11 -> -2653147.6 | E11: =IFERROR(D11/B11,0) -> -0.062146372 | F11: =IF(ABS(E11)>0.05,"REVIEW","") -> REVIEW
A12: ='Forecast '!E24 -> 45962 | B12: ='Forecast '!L24 -> 40090042 | C12: ='Forecast '!F24 -> 34684681 | D12: =C12-B12 -> -5405361.2 | E12: =IFERROR(D12/B12,0) -> -0.13483052 | F12: =IF(ABS(E12)>0.05,"REVIEW","") -> REVIEW
A13: ='Forecast '!E25 -> 45992 | B13: ='Forecast '!L25 -> 41196968 | C13: ='Forecast '!F25 -> 41657070 | D13: =C13-B13 -> 460102.32 | E13: =IFERROR(D13/B13,0) -> 0.011168354 | F13: =IF(ABS(E13)>0.05,"REVIEW","")
A14: Total | B14: =SUM(B2:B13) -> 4.4723541e+08 | C14: =SUM(C2:C13) -> 4.2481429e+08 | D14: =SUM(D2:D13) -> -22421128 | E14: =D14/B14 -> -0.05013272

Sheet PVM
A1: Category | B1: Dollar 2024 | C1: Dollar 2025 | D1: Bottles 2024 | E1: Bottles 2025 | F1: Price 2024 | G1: Price 2025 | H1: Mix 2024 | I1: Mix 2025 | J1: Price Effect | K1: Volume Effect | L1: Mix Effect | M1: Total Effect | N1: Actual Change | O1: % Variance | P1: Flag
A2: Brandy | B2: 14162342 | C2: 12151458 | D2: 1115164 | E2: 987761 | F2: =B2/D2 -> 12.699784 | G2: =C2/E2 -> 12.302022 | H2: =D2/$D$10 -> 0.035525807 | I2: =E2/$E$10 -> 0.032448671 | J2: =(G2-F2)*E2 -> -392893.51 | K2: =($E$10-$D$10)*H2*F2 -> -428398.62 | L2: =(I2-H2)*$E$10*F2 -> -1189592 | M2: =J2+K2+L2 -> -2010884.1 | N2: =C2-B2 -> -2010884.1 | O2: =IFERROR(N2/B2,0) -> -0.1419881 | P2: =IF(ABS(O2)>0.05,"REVIEW","") -> REVIEW
A3: Gin | B3: 9677368.7 | C3: 9096851.3 | D3: 595708 | E3: 549333 | F3: =B3/D3 -> 16.245155 | G3: =C3/E3 -> 16.559812 | H3: =D3/$D$10 -> 0.018977484 | I3: =E3/$E$10 -> 0.018045991 | J3: =(G3-F3)*E3 -> 172851.64 | K3: =($E$10-$D$10)*H3*F3 -> -292732.05 | L3: =(I3-H3)*$E$10*F3 -> -460637.01 | M3: =J3+K3+L3 -> -580517.42 | N3: =C3-B3 -> -580517.42 | O3: =IFERROR(N3/B3,0) -> -0.059987114 | P3: =IF(ABS(O3)>0.05,"REVIEW","") -> REVIEW
A4: Liqueurs | B4: 39965838 | C4: 39699622 | D4: 2778353 | E4: 2822040 | F4: =B4/D4 -> 14.384723 | G4: =C4/E4 -> 14.067703 | H4: =D4/$D$10 -> 0.08851006 | I4: =E4/$E$10 -> 0.092706077 | J4: =(G4-F4)*E4 -> -894641.7 | K4: =($E$10-$D$10)*H4*F4 -> -1208932.1 | L4: =(I4-H4)*$E$10*F4 -> 1837357.5 | M4: =J4+K4+L4 -> -266216.31 | N4: =C4-B4 -> -266216.31 | O4: =IFERROR(N4/B4,0) -> -0.0066610966 | P4: =IF(ABS(O4)>0.05,"REVIEW","")
A5: Other | B5: 34959620 | C5: 31728182 | D5: 2269527 | E5: 2134009 | F5: =B5/D5 -> 15.403923 | G5: =C5/E5 -> 14.867876 | H5: =D5/$D$10 -> 0.072300378 | I5: =E5/$E$10 -> 0.070103755 | J5: =(G5-F5)*E5 -> -1143929.1 | K5: =($E$10-$D$10)*H5*F5 -> -1057498.3 | L5: =(I5-H5)*$E$10*F5 -> -1030010.5 | M5: =J5+K5+L5 -> -3231438 | N5: =C5-B5 -> -3231438 | O5: =IFERROR(N5/B5,0) -> -0.092433442 | P5: =IF(ABS(O5)>0.05,"REVIEW","") -> REVIEW
A6: Rum | B6: 36797823 | C6: 33851775 | D6: 2416235 | E6: 2240677 | F6: =B6/D6 -> 15.229406 | G6: =C6/E6 -> 15.107833 | H6: =D6/$D$10 -> 0.076974058 | I6: =E6/$E$10 -> 0.073607877 | J6: =(G6-F6)*E6 -> -272404.12 | K6: =($E$10-$D$10)*H6*F6 -> -1113102.4 | L6: =(I6-H6)*$E$10*F6 -> -1560541.6 | M6: =J6+K6+L6 -> -2946048.1 | N6: =C6-B6 -> -2946048.1 | O6: =IFERROR(N6/B6,0) -> -0.080060392 | P6: =IF(ABS(O6)>0.05,"REVIEW","") -> REVIEW
A7: Tequila/Mezcal | B7: 46241499 | C7: 44269303 | D7: 1986930 | E7: 1950324 | F7: =B7/D7 -> 23.272837 | G7: =C7/E7 -> 22.698435 | H7: =D7/$D$10 -> 0.063297678 | I7: =E7/$E$10 -> 0.064069569 | J7: =(G7-F7)*E7 -> -1120270.4 | K7: =($E$10-$D$10)*H7*F7 -> -1398765.4 | L7: =(I7-H7)*$E$10*F7 -> 546839.94 | M7: =J7+K7+L7 -> -1972195.9 | N7: =C7-B7 -> -1972195.9 | O7: =IFERROR(N7/B7,0) -> -0.042649913 | P7: =IF(ABS(O7)>0.05,"REVIEW","")
A8: Vodka | B8: 94552481 | C8: 91185254 | D8: 8531713 | E8: 8347999 | F8: =B8/D8 -> 11.082473 | G8: =C8/E8 -> 10.923007 | H8: =D8/$D$10 -> 0.27179499 | I8: =E8/$E$10 -> 0.27423787 | J8: =(G8-F8)*E8 -> -1331221.1 | K8: =($E$10-$D$10)*H8*F8 -> -2860130.9 | L8: =(I8-H8)*$E$10*F8 -> 824125.45 | M8: =J8+K8+L8 -> -3367226.6 | N8: =C8-B8 -> -3367226.6 | O8: =IFERROR(N8/B8,0) -> -0.03561225 | P8: =IF(ABS(O8)>0.05,"REVIEW","")
A9: Whiskey | B9: 1.7087844e+08 | C9: 1.6283184e+08 | D9: 11696621 | E9: 11408580 | F9: =B9/D9 -> 14.609214 | G9: =C9/E9 -> 14.272753 | H9: =D9/$D$10 -> 0.37261954 | I9: =E9/$E$10 -> 0.37478019 | J9: =(G9-F9)*E9 -> -3838548.5 | K9: =($E$10-$D$10)*H9*F9 -> -5168925.4 | L9: =(I9-H9)*$E$10*F9 -> 960872.71 | M9: =J9+K9+L9 -> -8046601.2 | N9: =C9-B9 -> -8046601.2 | O9: =IFERROR(N9/B9,0) -> -0.047089621 | P9: =IF(ABS(O9)>0.05,"REVIEW","")
A10: TOTAL | B10: =SUM(B2:B9) -> 4.4723541e+08 | C10: =SUM(C2:C9) -> 4.2481429e+08 | D10: =SUM(D2:D9) -> 31390251 | E10: =SUM(E2:E9) -> 30440723 | F10: =B10/D10 -> 14.24759 | G10: =C10/E10 -> 13.95546 | H10: =SUM(H2:H9) -> 1 | I10: =SUM(I2:I9) -> 1 | J10: =SUM(J2:J9) -> -8821056.8 | K10: =SUM(K2:K9) -> -13528485 | L10: =SUM(L2:L9) -> -71585.53 | M10: =SUM(M2:M9) -> -22421128 | N10: =SUM(N2:N9) -> -22421128 | O10: =N10/B10 -> -0.05013272
A13: 2024 Sales | B13: =B10 -> 4.4723541e+08
A14: Price | B14: =J10 -> -8821056.8
A15: Volume | B15: =K10 -> -13528485
A16: Mix | B16: =L10 -> -71585.53
A17: 2025 Sales | B17: =C10 -> 4.2481429e+08

Sheet Monthly_Category
A1: Year | B1: Start of Month | C1: category_name | D1: category | E1: sum_sale_bottles | F1: sum_sale_dollars | G1: sum_sale_liters | H1: transactions
A2: 2021 | B2: 44378 | C2: AGED DARK RUM | D2: {=_xlfn.IFS( ISNUMBER(SEARCH("WHISK",C2)),"Whiskey", ISNUMBER(SEARCH("BOURBON",C2)),"Whiskey", ISNUMBER(SEARCH("SCOTCH",C2)),"Whiskey", ISNUMBER(SEARCH("RYE",C2)),"Whiskey", ISNUMBER(SEARCH("VODKA",C2)),"Vodka", ISNUMBER(SEARCH("TEQUILA",C2)),"Tequila/Mezcal", ISNUMBER(SEARCH("MEZCAL",C2)),"Tequila/Mezcal", ISNUMBER(SEARCH("RUM",C2)),"Rum", ISNUMBER(SEARCH("BRAND",C2)),"Brandy", ISNUMBER(SEARCH("COGNAC",C2)),"Brandy", ISNUMBER(SEARCH("LIQUEUR",C2)),"Liqueurs", ISNUMBER(SEARCH("CORDIAL",C2)),"Liqueurs", ISNUMBER(SEARCH("SCHNAPP",C2)),"Liqueurs", ISNUMBER(SEARCH("GIN",C2)),"Gin", TRUE,"Other")} -> Rum | E2: 5026 | F2: 105773.77 | G2: 4061 | H2: 800
A3: 2021 | B3: 44378 | C3: AMERICAN BRANDIES | D3: {=_xlfn.IFS( ISNUMBER(SEARCH("WHISK",C3)),"Whiskey", ISNUMBER(SEARCH("BOURBON",C3)),"Whiskey", ISNUMBER(SEARCH("SCOTCH",C3)),"Whiskey", ISNUMBER(SEARCH("RYE",C3)),"Whiskey", ISNUMBER(SEARCH("VODKA",C3)),"Vodka", ISNUMBER(SEARCH("TEQUILA",C3)),"Tequila/Mezcal", ISNUMBER(SEARCH("MEZCAL",C3)),"Tequila/Mezcal", ISNUMBER(SEARCH("RUM",C3)),"Rum", ISNUMBER(SEARCH("BRAND",C3)),"Brandy", ISNUMBER(SEARCH("COGNAC",C3)),"Brandy", ISNUMBER(SEARCH("LIQUEUR",C3)),"Liqueurs", ISNUMBER(SEARCH("CORDIAL",C3)),"Liqueurs", ISNUMBER(SEARCH("SCHNAPP",C3)),"Liqueurs", ISNUMBER(SEARCH("GIN",C3)),"Gin", TRUE,"Other")} -> Brandy | E3: 56089 | F3: 377706.06 | G3: 30324.01 | H3: 5059
A4: 2021 | B4: 44378 | C4: AMERICAN CORDIALS & LIQUEURSS | D4: {=_xlfn.IFS( ISNUMBER(SEARCH("WHISK",C4)),"Whiskey", ISNUMBER(SEARCH("BOURBON",C4)),"Whiskey", ISNUMBER(SEARCH("SCOTCH",C4)),"Whiskey", ISNUMBER(SEARCH("RYE",C4)),"Whiskey", ISNUMBER(SEARCH("VODKA",C4)),"Vodka", ISNUMBER(SEARCH("TEQUILA",C4)),"Tequila/Mezcal", ISNUMBER(SEARCH("MEZCAL",C4)),"Tequila/Mezcal", ISNUMBER(SEARCH("RUM",C4)),"Rum", ISNUMBER(SEARCH("BRAND",C4)),"Brandy", ISNUMBER(SEARCH("COGNAC",C4)),"Brandy", ISNUMBER(SEARCH("LIQUEUR",C4)),"Liqueurs", ISNUMBER(SEARCH("CORDIAL",C4)),"Liqueurs", ISNUMBER(SEARCH("SCHNAPP",C4)),"Liqueurs", ISNUMBER(SEARCH("GIN",C4)),"Gin", TRUE,"Other")} -> Liqueurs | E4: 40402 | F4: 384991.39 | G4: 20433.93 | H4: 5462
A5: 2021 | B5: 44378 | C5: AMERICAN DISTILLED SPIRITS SPECIALTY | D5: {=_xlfn.IFS( ISNUMBER(SEARCH("WHISK",C5)),"Whiskey", ISNUMBER(SEARCH("BOURBON",C5)),"Whiskey", ISNUMBER(SEARCH("SCOTCH",C5)),"Whiskey", ISNUMBER(SEARCH("RYE",C5)),"Whiskey", ISNUMBER(SEARCH("VODKA",C5)),"Vodka", ISNUMBER(SEARCH("TEQUILA",C5)),"Tequila/Mezcal", ISNUMBER(SEARCH("MEZCAL",C5)),"Tequila/Mezcal", ISNUMBER(SEARCH("RUM",C5)),"Rum", ISNUMBER(SEARCH("BRAND",C5)),"Brandy", ISNUMBER(SEARCH("COGNAC",C5)),"Brandy", ISNUMBER(SEARCH("LIQUEUR",C5)),"Liqueurs", ISNUMBER(SEARCH("CORDIAL",C5)),"Liqueurs", ISNUMBER(SEARCH("SCHNAPP",C5)),"Liqueurs", ISNUMBER(SEARCH("GIN",C5)),"Gin", TRUE,"Other")} -> Other | E5: 6318 | F5: 124077.32 | G5: 4754.25 | H5: 872
A6: 2021 | B6: 44378 | C6: AMERICAN DRY GINS | D6: {=_xlfn.IFS( ISNUMBER(SEARCH("WHISK",C6)),"Whiskey", ISNUMBER(SEARCH("BOURBON",C6)),"Whiskey", ISNUMBER(SEARCH("SCOTCH",C6)),"Whiskey", ISNUMBER(SEARCH("RYE",C6)),"Whiskey", ISNUMBER(SEARCH("VODKA",C6)),"Vodka", ISNUMBER(SEARCH("TEQUILA",C6)),"Tequila/Mezcal", ISNUMBER(SEARCH("MEZCAL",C6)),"Tequila/Mezcal", ISNUMBER(SEARCH("RUM",C6)),"Rum", ISNUMBER(SEARCH("BRAND",C6)),"Brandy", ISNUMBER(SEARCH("COGNAC",C6)),"Brandy", ISNUMBER(SEARCH("LIQUEUR",C6)),"Liqueurs", ISNUMBER(SEARCH("CORDIAL",C6)),"Liqueurs", ISNUMBER(SEARCH("SCHNAPP",C6)),"Liqueurs", ISNUMBER(SEARCH("GIN",C6)),"Gin", TRUE,"Other")} -> Gin | E6: 40517 | F6: 347140.36 | G6: 32409.64 | H6: 3926
A7: 2021 | B7: 44378 | C7: AMERICAN FLAVORED VODKA | D7: {=_xlfn.IFS( ISNUMBER(SEARCH("WHISK",C7)),"Whiskey", ISNUMBER(SEARCH("BOURBON",C7)),"Whiskey", ISNUMBER(SEARCH("SCOTCH",C7)),"Whiskey", ISNUMBER(SEARCH("RYE",C7)),"Whiskey", ISNUMBER(SEARCH("VODKA",C7)),"Vodka", ISNUMBER(SEARCH("TEQUILA",C7)),"Tequila/Mezcal", ISNUMBER(SEARCH("MEZCAL",C7)),"Tequila/Mezcal", ISNUMBER(SEARCH("RUM",C7)),"Rum", ISNUMBER(SEARCH("BRAND",C7)),"Brandy", ISNUMBER(SEARCH("COGNAC",C7)),"Brandy", ISNUMBER(SEARCH("LIQUEUR",C7)),"Liqueurs", ISNUMBER(SEARCH("CORDIAL",C7)),"Liqueurs", ISNUMBER(SEARCH("SCHNAPP",C7)),"Liqueurs", ISNUMBER(SEARCH("GIN",C7)),"Gin", TRUE,"Other")} -> Vodka | E7: 89407 | F7: 965550.13 | G7: 64752.06 | H7: 10790
A8: 2021 | B8: 44378 | C8: AMERICAN SCHNAPPS | D8: {=_xlfn.IFS( ISNUMBER(SEARCH("WHISK",C8)),"Whiskey", ISNUMBER(SEARCH("BOURBON",C8)),"Whiskey", ISNUMBER(SEARCH("SCOTCH",C8)),"Whiskey", ISNUMBER(SEARCH("RYE",C8)),"Whiskey", ISNUMBER(SEARCH("VODKA",C8)),"Vodka", ISNUMBER(SEARCH("TEQUILA",C8)),"Tequila/Mezcal", ISNUMBER(SEARCH("MEZCAL",C8)),"Tequila/Mezcal", ISNUMBER(SEARCH("RUM",C8)),"Rum", ISNUMBER(SEARCH("BRAND",C8)),"Brandy", ISNUMBER(SEARCH("COGNAC",C8)),"Brandy", ISNUMBER(SEARCH("LIQUEUR",C8)),"Liqueurs", ISNUMBER(SEARCH("CORDIAL",C8)),"Liqueurs", ISNUMBER(SEARCH("SCHNAPP",C8)),"Liqueurs", ISNUMBER(SEARCH("GIN",C8)),"Gin", TRUE,"Other")} -> Liqueurs | E8: 64267 | F8: 531857.12 | G8: 41582.6 | H8: 6476
A9: 2021 | B9: 44378 | C9: AMERICAN SLOE GINS | D9: {=_xlfn.IFS( ISNUMBER(SEARCH("WHISK",C9)),"Whiskey", ISNUMBER(SEARCH("BOURBON",C9)),"Whiskey", ISNUMBER(SEARCH("SCOTCH",C9)),"Whiskey", ISNUMBER(SEARCH("RYE",C9)),"Whiskey", ISNUMBER(SEARCH("VODKA",C9)),"Vodka", ISNUMBER(SEARCH("TEQUILA",C9)),"Tequila/Mezcal", ISNUMBER(SEARCH("MEZCAL",C9)),"Tequila/Mezcal", ISNUMBER(SEARCH("RUM",C9)),"Rum", ISNUMBER(SEARCH("BRAND",C9)),"Brandy", ISNUMBER(SEARCH("COGNAC",C9)),"Brandy", ISNUMBER(SEARCH("LIQUEUR",C9)),"Liqueurs", ISNUMBER(SEARCH("CORDIAL",C9)),"Liqueurs", ISNUMBER(SEARCH("SCHNAPP",C9)),"Liqueurs", ISNUMBER(SEARCH("GIN",C9)),"Gin", TRUE,"Other")} -> Gin | E9: 252 | F9: 2048.76 | G9: 252 | H9: 73
A10: 2021 | B10: 44378 | C10: AMERICAN VODKAS | D10: {=_xlfn.IFS( ISNUMBER(SEARCH("WHISK",C10)),"Whiskey", ISNUMBER(SEARCH("BOURBON",C10)),"Whiskey", ISNUMBER(SEARCH("SCOTCH",C10)),"Whiskey", ISNUMBER(SEARCH("RYE",C10)),"Whiskey", ISNUMBER(SEARCH("VODKA",C10)),"Vodka", ISNUMBER(SEARCH("TEQUILA",C10)),"Tequila/Mezcal", ISNUMBER(SEARCH("MEZCAL",C10)),"Tequila/Mezcal", ISNUMBER(SEARCH("RUM",C10)),"Rum", ISNUMBER(SEARCH("BRAND",C10)),"Brandy", ISNUMBER(SEARCH("COGNAC",C10)),"Brandy", ISNUMBER(SEARCH("LIQUEUR",C10)),"Liqueurs", ISNUMBER(SEARCH("CORDIAL",C10)),"Liqueurs", ISNUMBER(SEARCH("SCHNAPP",C10)),"Liqueurs", ISNUMBER(SEARCH("GIN",C10)),"Gin", TRUE,"Other")} -> Vodka | E10: 526149 | F10: 5204743.4 | G10: 485603.28 | H10: 32930
A11: 2021 | B11: 44378 | C11: BLENDED WHISKIES | D11: {=_xlfn.IFS( ISNUMBER(SEARCH("WHISK",C11)),"Whiskey", ISNUMBER(SEARCH("BOURBON",C11)),"Whiskey", ISNUMBER(SEARCH("SCOTCH",C11)),"Whiskey", ISNUMBER(SEARCH("RYE",C11)),"Whiskey", ISNUMBER(SEARCH("VODKA",C11)),"Vodka", ISNUMBER(SEARCH("TEQUILA",C11)),"Tequila/Mezcal", ISNUMBER(SEARCH("MEZCAL",C11)),"Tequila/Mezcal", ISNUMBER(SEARCH("RUM",C11)),"Rum", ISNUMBER(SEARCH("BRAND",C11)),"Brandy", ISNUMBER(SEARCH("COGNAC",C11)),"Brandy", ISNUMBER(SEARCH("LIQUEUR",C11)),"Liqueurs", ISNUMBER(SEARCH("CORDIAL",C11)),"Liqueurs", ISNUMBER(SEARCH("SCHNAPP",C11)),"Liqueurs", ISNUMBER(SEARCH("GIN",C11)),"Gin", TRUE,"Other")} -> Whiskey | E11: 77666 | F11: 952919.96 | G11: 66502.29 | H11: 8891
A12: 2021 | B12: 44378 | C12: BOTTLED IN BOND BOURBON | D12: {=_xlfn.IFS( ISNUMBER(SEARCH("WHISK",C12)),"Whiskey", ISNUMBER(SEARCH("BOURBON",C12)),"Whiskey", ISNUMBER(SEARCH("SCOTCH",C12)),"Whiskey", ISNUMBER(SEARCH("RYE",C12)),"Whiskey", ISNUMBER(SEARCH("VODKA",C12)),"Vodka", ISNUMBER(SEARCH("TEQUILA",C12)),"Tequila/Mezcal", ISNUMBER(SEARCH("MEZCAL",C12)),"Tequila/Mezcal", ISNUMBER(SEARCH("RUM",C12)),"Rum", ISNUMBER(SEARCH("BRAND",C12)),"Brandy", ISNUMBER(SEARCH("COGNAC",C12)),"Brandy", ISNUMBER(SEARCH("LIQUEUR",C12)),"Liqueurs", ISNUMBER(SEARCH("CORDIAL",C12)),"Liqueurs", ISNUMBER(SEARCH("SCHNAPP",C12)),"Liqueurs", ISNUMBER(SEARCH("GIN",C12)),"Gin", TRUE,"Other")} -> Whiskey | E12: 1428 | F12: 36977.23 | G12: 1071 | H12: 241
A13: 2021 | B13: 44378 | C13: CANADIAN WHISKIES | D13: {=_xlfn.IFS( ISNUMBER(SEARCH("WHISK",C13)),"Whiskey", ISNUMBER(SEARCH("BOURBON",C13)),"Whiskey", ISNUMBER(SEARCH("SCOTCH",C13)),"Whiskey", ISNUMBER(SEARCH("RYE",C13)),"Whiskey", ISNUMBER(SEARCH("VODKA",C13)),"Vodka", ISNUMBER(SEARCH("TEQUILA",C13)),"Tequila/Mezcal", ISNUMBER(SEARCH("MEZCAL",C13)),"Tequila/Mezcal", ISNUMBER(SEARCH("RUM",C13)),"Rum", ISNUMBER(SEARCH("BRAND",C13)),"Brandy", ISNUMBER(SEARCH("COGNAC",C13)),"Brandy", ISNUMBER(SEARCH("LIQUEUR",C13)),"Liqueurs", ISNUMBER(SEARCH("CORDIAL",C13)),"Liqueurs", ISNUMBER(SEARCH("SCHNAPP",C13)),"Liqueurs", ISNUMBER(SEARCH("GIN",C13)),"Gin", TRUE,"Other")} -> Whiskey | E13: 252179 | F13: 3731650.3 | G13: 258720.9 | H13: 18754
... A1080: 2024 | B1080: 45627 | C1080: AMERICAN SLOE GINS | D1080: {=_xlfn.IFS( ISNUMBER(SEARCH("WHISK",C1080)),"Whiskey", ISNUMBER(SEARCH("BOURBON",C1080)),"Whiskey", ISNUMBER(SEARCH("SCOTCH",C1080)),"Whiskey", ISNUMBER(SEARCH("RYE",C1080)),"Whiskey", ISNUMBER(SEARCH("VODKA",C1080)),"Vodka", ISNUMBER(SEARCH("TEQUILA",C1080)),"Tequila/Mezcal", ISNUMBER(SEARCH("MEZCAL",C1080)),"Tequila/Mezcal", ISNUMBER(SEARCH("RUM",C1080)),"Rum", ISNUMBER(SEARCH("BRAND",C1080)),"Brandy", ISNUMBER(SEARCH("COGNAC",C1080)),"Brandy", ISNUMBER(SEARCH("LIQUEUR",C1080)),"Liqueurs", ISNUMBER(SEARCH("CORDIAL",C1080)),"Liqueurs", ISNUMBER(SEARCH("SCHNAPP",C1080)),"Liqueurs", ISNUMBER(SEARCH("GIN",C1080)),"Gin", TRUE,"Other")} -> Gin | E1080: 276 | F1080: 2357.04 | G1080: 276 | H1080: 57
A1081: 2022 | B1081: 44562 | C1081: 100% AGAVE TEQUILA | D1081: {=_xlfn.IFS( ISNUMBER(SEARCH("WHISK",C1081)),"Whiskey", ISNUMBER(SEARCH("BOURBON",C1081)),"Whiskey", ISNUMBER(SEARCH("SCOTCH",C1081)),"Whiskey", ISNUMBER(SEARCH("RYE",C1081)),"Whiskey", ISNUMBER(SEARCH("VODKA",C1081)),"Vodka", ISNUMBER(SEARCH("TEQUILA",C1081)),"Tequila/Mezcal", ISNUMBER(SEARCH("MEZCAL",C1081)),"Tequila/Mezcal", ISNUMBER(SEARCH("RUM",C1081)),"Rum", ISNUMBER(SEARCH("BRAND",C1081)),"Brandy", ISNUMBER(SEARCH("COGNAC",C1081)),"Brandy", ISNUMBER(SEARCH("LIQUEUR",C1081)),"Liqueurs", ISNUMBER(SEARCH("CORDIAL",C1081)),"Liqueurs", ISNUMBER(SEARCH("SCHNAPP",C1081)),"Liqueurs", ISNUMBER(SEARCH("GIN",C1081)),"Gin", TRUE,"Other")} -> Tequila/Mezcal | E1081: 50549 | F1081: 1443274.9 | H1081: 5596
A1082: 2022 | B1082: 44562 | C1082: AGED DARK RUM | D1082: {=_xlfn.IFS( ISNUMBER(SEARCH("WHISK",C1082)),"Whiskey", ISNUMBER(SEARCH("BOURBON",C1082)),"Whiskey", ISNUMBER(SEARCH("SCOTCH",C1082)),"Whiskey", ISNUMBER(SEARCH("RYE",C1082)),"Whiskey", ISNUMBER(SEARCH("VODKA",C1082)),"Vodka", ISNUMBER(SEARCH("TEQUILA",C1082)),"Tequila/Mezcal", ISNUMBER(SEARCH("MEZCAL",C1082)),"Tequila/Mezcal", ISNUMBER(SEARCH("RUM",C1082)),"Rum", ISNUMBER(SEARCH("BRAND",C1082)),"Brandy", ISNUMBER(SEARCH("COGNAC",C1082)),"Brandy", ISNUMBER(SEARCH("LIQUEUR",C1082)),"Liqueurs", ISNUMBER(SEARCH("CORDIAL",C1082)),"Liqueurs", ISNUMBER(SEARCH("SCHNAPP",C1082)),"Liqueurs", ISNUMBER(SEARCH("GIN",C1082)),"Gin", TRUE,"Other")} -> Rum | E1082: 3840 | F1082: 79755.8 | H1082: 674
A1083: 2022 | B1083: 44562 | C1083: AMERICAN BRANDIES | D1083: {=_xlfn.IFS( ISNUMBER(SEARCH("WHISK",C1083)),"Whiskey", ISNUMBER(SEARCH("BOURBON",C1083)),"Whiskey", ISNUMBER(SEARCH("SCOTCH",C1083)),"Whiskey", ISNUMBER(SEARCH("RYE",C1083)),"Whiskey", ISNUMBER(SEARCH("VODKA",C1083)),"Vodka", ISNUMBER(SEARCH("TEQUILA",C1083)),"Tequila/Mezcal", ISNUMBER(SEARCH("MEZCAL",C1083)),"Tequila/Mezcal", ISNUMBER(SEARCH("RUM",C1083)),"Rum", ISNUMBER(SEARCH("BRAND",C1083)),"Brandy", ISNUMBER(SEARCH("COGNAC",C1083)),"Brandy", ISNUMBER(SEARCH("LIQUEUR",C1083)),"Liqueurs", ISNUMBER(SEARCH("CORDIAL",C1083)),"Liqueurs", ISNUMBER(SEARCH("SCHNAPP",C1083)),"Liqueurs", ISNUMBER(SEARCH("GIN",C1083)),"Gin", TRUE,"Other")} -> Brandy | E1083: 61714 | F1083: 407451.14 | H1083: 5407
A1084: 2022 | B1084: 44562 | C1084: AMERICAN DISTILLED SPIRITS SPECIALTY | D1084: {=_xlfn.IFS( ISNUMBER(SEARCH("WHISK",C1084)),"Whiskey", ISNUMBER(SEARCH("BOURBON",C1084)),"Whiskey", ISNUMBER(SEARCH("SCOTCH",C1084)),"Whiskey", ISNUMBER(SEARCH("RYE",C1084)),"Whiskey", ISNUMBER(SEARCH("VODKA",C1084)),"Vodka", ISNUMBER(SEARCH("TEQUILA",C1084)),"Tequila/Mezcal", ISNUMBER(SEARCH("MEZCAL",C1084)),"Tequila/Mezcal", ISNUMBER(SEARCH("RUM",C1084)),"Rum", ISNUMBER(SEARCH("BRAND",C1084)),"Brandy", ISNUMBER(SEARCH("COGNAC",C1084)),"Brandy", ISNUMBER(SEARCH("LIQUEUR",C1084)),"Liqueurs", ISNUMBER(SEARCH("CORDIAL",C1084)),"Liqueurs", ISNUMBER(SEARCH("SCHNAPP",C1084)),"Liqueurs", ISNUMBER(SEARCH("GIN",C1084)),"Gin", TRUE,"Other")} -> Other | E1084: 4903 | F1084: 88699.48 | H1084: 736
A1085: 2022 | B1085: 44562 | C1085: AMERICAN DRY GINS | D1085: {=_xlfn.IFS( ISNUMBER(SEARCH("WHISK",C1085)),"Whiskey", ISNUMBER(SEARCH("BOURBON",C1085)),"Whiskey", ISNUMBER(SEARCH("SCOTCH",C1085)),"Whiskey", ISNUMBER(SEARCH("RYE",C1085)),"Whiskey", ISNUMBER(SEARCH("VODKA",C1085)),"Vodka", ISNUMBER(SEARCH("TEQUILA",C1085)),"Tequila/Mezcal", ISNUMBER(SEARCH("MEZCAL",C1085)),"Tequila/Mezcal", ISNUMBER(SEARCH("RUM",C1085)),"Rum", ISNUMBER(SEARCH("BRAND",C1085)),"Brandy", ISNUMBER(SEARCH("COGNAC",C1085)),"Brandy", ISNUMBER(SEARCH("LIQUEUR",C1085)),"Liqueurs", ISNUMBER(SEARCH("CORDIAL",C1085)),"Liqueurs", ISNUMBER(SEARCH("SCHNAPP",C1085)),"Liqueurs", ISNUMBER(SEARCH("GIN",C1085)),"Gin", TRUE,"Other")} -> Gin | E1085: 20425 | F1085: 228747.06 | H1085: 2279
A1086: 2022 | B1086: 44562 | C1086: AMERICAN FLAVORED VODKA | D1086: {=_xlfn.IFS( ISNUMBER(SEARCH("WHISK",C1086)),"Whiskey", ISNUMBER(SEARCH("BOURBON",C1086)),"Whiskey", ISNUMBER(SEARCH("SCOTCH",C1086)),"Whiskey", ISNUMBER(SEARCH("RYE",C1086)),"Whiskey", ISNUMBER(SEARCH("VODKA",C1086)),"Vodka", ISNUMBER(SEARCH("TEQUILA",C1086)),"Tequila/Mezcal", ISNUMBER(SEARCH("MEZCAL",C1086)),"Tequila/Mezcal", ISNUMBER(SEARCH("RUM",C1086)),"Rum", ISNUMBER(SEARCH("BRAND",C1086)),"Brandy", ISNUMBER(SEARCH("COGNAC",C1086)),"Brandy", ISNUMBER(SEARCH("LIQUEUR",C1086)),"Liqueurs", ISNUMBER(SEARCH("CORDIAL",C1086)),"Liqueurs", ISNUMBER(SEARCH("SCHNAPP",C1086)),"Liqueurs", ISNUMBER(SEARCH("GIN",C1086)),"Gin", TRUE,"Other")} -> Vodka | E1086: 63611 | F1086: 676141.99 | H1086: 8028
A1087: 2022 | B1087: 44562 | C1087: AMERICAN SCHNAPPS | D1087: {=_xlfn.IFS( ISNUMBER(SEARCH("WHISK",C1087)),"Whiskey", ISNUMBER(SEARCH("BOURBON",C1087)),"Whiskey", ISNUMBER(SEARCH("SCOTCH",C1087)),"Whiskey", ISNUMBER(SEARCH("RYE",C1087)),"Whiskey", ISNUMBER(SEARCH("VODKA",C1087)),"Vodka", ISNUMBER(SEARCH("TEQUILA",C1087)),"Tequila/Mezcal", ISNUMBER(SEARCH("MEZCAL",C1087)),"Tequila/Mezcal", ISNUMBER(SEARCH("RUM",C1087)),"Rum", ISNUMBER(SEARCH("BRAND",C1087)),"Brandy", ISNUMBER(SEARCH("COGNAC",C1087)),"Brandy", ISNUMBER(SEARCH("LIQUEUR",C1087)),"Liqueurs", ISNUMBER(SEARCH("CORDIAL",C1087)),"Liqueurs", ISNUMBER(SEARCH("SCHNAPP",C1087)),"Liqueurs", ISNUMBER(SEARCH("GIN",C1087)),"Gin", TRUE,"Other")} -> Liqueurs | E1087: 55064 | F1087: 426143.71 | H1087: 6165
A1088: 2022 | B1088: 44562 | C1088: BLENDED WHISKIES | D1088: {=_xlfn.IFS( ISNUMBER(SEARCH("WHISK",C1088)),"Whiskey", ISNUMBER(SEARCH("BOURBON",C1088)),"Whiskey", ISNUMBER(SEARCH("SCOTCH",C1088)),"Whiskey", ISNUMBER(SEARCH("RYE",C1088)),"Whiskey", ISNUMBER(SEARCH("VODKA",C1088)),"Vodka", ISNUMBER(SEARCH("TEQUILA",C1088)),"Tequila/Mezcal", ISNUMBER(SEARCH("MEZCAL",C1088)),"Tequila/Mezcal", ISNUMBER(SEARCH("RUM",C1088)),"Rum", ISNUMBER(SEARCH("BRAND",C1088)),"Brandy", ISNUMBER(SEARCH("COGNAC",C1088)),"Brandy", ISNUMBER(SEARCH("LIQUEUR",C1088)),"Liqueurs", ISNUMBER(SEARCH("CORDIAL",C1088)),"Liqueurs", ISNUMBER(SEARCH("SCHNAPP",C1088)),"Liqueurs", ISNUMBER(SEARCH("GIN",C1088)),"Gin", TRUE,"Other")} -> Whiskey | E1088: 66930 | F1088: 841707.98 | H1088: 7940
A1089: 2022 | B1089: 44562 | C1089: CANADIAN WHISKIES | D1089: {=_xlfn.IFS( ISNUMBER(SEARCH("WHISK",C1089)),"Whiskey", ISNUMBER(SEARCH("BOURBON",C1089)),"Whiskey", ISNUMBER(SEARCH("SCOTCH",C1089)),"Whiskey", ISNUMBER(SEARCH("RYE",C1089)),"Whiskey", ISNUMBER(SEARCH("VODKA",C1089)),"Vodka", ISNUMBER(SEARCH("TEQUILA",C1089)),"Tequila/Mezcal", ISNUMBER(SEARCH("MEZCAL",C1089)),"Tequila/Mezcal", ISNUMBER(SEARCH("RUM",C1089)),"Rum", ISNUMBER(SEARCH("BRAND",C1089)),"Brandy", ISNUMBER(SEARCH("COGNAC",C1089)),"Brandy", ISNUMBER(SEARCH("LIQUEUR",C1089)),"Liqueurs", ISNUMBER(SEARCH("CORDIAL",C1089)),"Liqueurs", ISNUMBER(SEARCH("SCHNAPP",C1089)),"Liqueurs", ISNUMBER(SEARCH("GIN",C1089)),"Gin", TRUE,"Other")} -> Whiskey | E1089: 197568 | F1089: 2930227.6 | H1089: 17031
A1090: 2022 | B1090: 44562 | C1090: COCKTAILS/RTD | D1090: {=_xlfn.IFS( ISNUMBER(SEARCH("WHISK",C1090)),"Whiskey", ISNUMBER(SEARCH("BOURBON",C1090)),"Whiskey", ISNUMBER(SEARCH("SCOTCH",C1090)),"Whiskey", ISNUMBER(SEARCH("RYE",C1090)),"Whiskey", ISNUMBER(SEARCH("VODKA",C1090)),"Vodka", ISNUMBER(SEARCH("TEQUILA",C1090)),"Tequila/Mezcal", ISNUMBER(SEARCH("MEZCAL",C1090)),"Tequila/Mezcal", ISNUMBER(SEARCH("RUM",C1090)),"Rum", ISNUMBER(SEARCH("BRAND",C1090)),"Brandy", ISNUMBER(SEARCH("COGNAC",C1090)),"Brandy", ISNUMBER(SEARCH("LIQUEUR",C1090)),"Liqueurs", ISNUMBER(SEARCH("CORDIAL",C1090)),"Liqueurs", ISNUMBER(SEARCH("SCHNAPP",C1090)),"Liqueurs", ISNUMBER(SEARCH("GIN",C1090)),"Gin", TRUE,"Other")} -> Other | E1090: 34095 | F1090: 388368.21 | H1090: 4933
A1091: 2022 | B1091: 44562 | C1091: COFFEE LIQUEURS | D1091: {=_xlfn.IFS( ISNUMBER(SEARCH("WHISK",C1091)),"Whiskey", ISNUMBER(SEARCH("BOURBON",C1091)),"Whiskey", ISNUMBER(SEARCH("SCOTCH",C1091)),"Whiskey", ISNUMBER(SEARCH("RYE",C1091)),"Whiskey", ISNUMBER(SEARCH("VODKA",C1091)),"Vodka", ISNUMBER(SEARCH("TEQUILA",C1091)),"Tequila/Mezcal", ISNUMBER(SEARCH("MEZCAL",C1091)),"Tequila/Mezcal", ISNUMBER(SEARCH("RUM",C1091)),"Rum", ISNUMBER(SEARCH("BRAND",C1091)),"Brandy", ISNUMBER(SEARCH("COGNAC",C1091)),"Brandy", ISNUMBER(SEARCH("LIQUEUR",C1091)),"Liqueurs", ISNUMBER(SEARCH("CORDIAL",C1091)),"Liqueurs", ISNUMBER(SEARCH("SCHNAPP",C1091)),"Liqueurs", ISNUMBER(SEARCH("GIN",C1091)),"Gin", TRUE,"Other")} -> Liqueurs | E1091: 7441 | F1091: 140008.21 | H1091: 815
A1092: 2022 | B1092: 44562 | C1092: CREAM LIQUEURS | D1092: {=_xlfn.IFS( ISNUMBER(SEARCH("WHISK",C1092)),"Whiskey", ISNUMBER(SEARCH("BOURBON",C1092)),"Whiskey", ISNUMBER(SEARCH("SCOTCH",C1092)),"Whiskey", ISNUMBER(SEARCH("RYE",C1092)),"Whiskey", ISNUMBER(SEARCH("VODKA",C1092)),"Vodka", ISNUMBER(SEARCH("TEQUILA",C1092)),"Tequila/Mezcal", ISNUMBER(SEARCH("MEZCAL",C1092)),"Tequila/Mezcal", ISNUMBER(SEARCH("RUM",C1092)),"Rum", ISNUMBER(SEARCH("BRAND",C1092)),"Brandy", ISNUMBER(SEARCH("COGNAC",C1092)),"Brandy", ISNUMBER(SEARCH("LIQUEUR",C1092)),"Liqueurs", ISNUMBER(SEARCH("CORDIAL",C1092)),"Liqueurs", ISNUMBER(SEARCH("SCHNAPP",C1092)),"Liqueurs", ISNUMBER(SEARCH("GIN",C1092)),"Gin", TRUE,"Other")} -> Liqueurs | E1092: 34245 | F1092: 684970.12 | H1092: 5192
... A2671: 2025 | B2671: 45992 | C2671: MEZCAL | D2671: {=_xlfn.IFS( ISNUMBER(SEARCH("WHISK",C2671)),"Whiskey", ISNUMBER(SEARCH("BOURBON",C2671)),"Whiskey", ISNUMBER(SEARCH("SCOTCH",C2671)),"Whiskey", ISNUMBER(SEARCH("RYE",C2671)),"Whiskey", ISNUMBER(SEARCH("VODKA",C2671)),"Vodka", ISNUMBER(SEARCH("TEQUILA",C2671)),"Tequila/Mezcal", ISNUMBER(SEARCH("MEZCAL",C2671)),"Tequila/Mezcal", ISNUMBER(SEARCH("RUM",C2671)),"Rum", ISNUMBER(SEARCH("BRAND",C2671)),"Brandy", ISNUMBER(SEARCH("COGNAC",C2671)),"Brandy", ISNUMBER(SEARCH("LIQUEUR",C2671)),"Liqueurs", ISNUMBER(SEARCH("CORDIAL",C2671)),"Liqueurs", ISNUMBER(SEARCH("SCHNAPP",C2671)),"Liqueurs", ISNUMBER(SEARCH("GIN",C2671)),"Gin", TRUE,"Other")} -> Tequila/Mezcal | E2671: 1594 | F2671: 46550 | H2671: 257

Sheet Line Chart
A1: category | B1: (All)
A3: Row Labels | B3: Sum of sum_sale_dollars
A4: Jan | B4: 1.5289564e+08
A5: Feb | B5: 1.5761691e+08
A6: Mar | B6: 1.7096718e+08
A7: Apr | B7: 1.7428656e+08
A8: May | B8: 1.8424144e+08
A9: Jun | B9: 1.9141547e+08
A10: Jul | B10: 1.7846616e+08
A11: Aug | B11: 1.8840712e+08
A12: Sep | B12: 1.7711838e+08
A13: Oct | B13: 2.0078684e+08
A14: Nov | B14: 1.8958581e+08
A15: Dec | B15: 2.0923639e+08
A16: Grand Total | B16: 2.1750239e+09
